[
{"id":"1","tittle":"Smartphone X1","code":"PRD-1001","category":"Electronics","brand":"Nexa","price":3999000,"stock":35},
{"id":"2","tittle":"Wireless Earbuds","code":"PRD-1002","category":"Electronics","brand":"Aurora","price":799000,"stock":78},
{"id":"3","tittle":"Gaming Keyboard","code":"PRD-1003","category":"Electronics","brand":"Pulse","price":1299000,"stock":24},
{"id":"4","tittle":"Office Chair","code":"PRD-1004","category":"Furniture","brand":"ErgoSafe","price":1850000,"stock":18},
{"id":"5","tittle":"Coffee Maker","code":"PRD-1005","category":"Kitchen","brand":"Culina","price":950000,"stock":42},
{"id":"6","tittle":"Yoga Mat","code":"PRD-1006","category":"Fitness","brand":"FlexFit","price":250000,"stock":66},
{"id":"7","tittle":"LED Monitor 24","code":"PRD-1007","category":"Electronics","brand":"VisionPro","price":2350000,"stock":19},
{"id":"8","tittle":"Bluetooth Speaker","code":"PRD-1008","category":"Electronics","brand":"SoundWave","price":550000,"stock":52},
{"id":"9","tittle":"Smartwatch S2","code":"PRD-1009","category":"Electronics","brand":"Tempo","price":1299000,"stock":29},
{"id":"10","tittle":"Air Purifier","code":"PRD-1010","category":"Home","brand":"PureAir","price":1590000,"stock":14},
{"id":"11","tittle":"Running Shoes","code":"PRD-1011","category":"Fashion","brand":"Stride","price":850000,"stock":30},
{"id":"12","tittle":"Backpack Traveler","code":"PRD-1012","category":"Fashion","brand":"Nomad","price":420000,"stock":55},
{"id":"13","tittle":"Wall Clock","code":"PRD-1013","category":"Home","brand":"Tempo","price":175000,"stock":80},
{"id":"14","tittle":"Desk Lamp","code":"PRD-1014","category":"Home","brand":"Lumen","price":225000,"stock":48},
{"id":"15","tittle":"Kitchen Knife Set","code":"PRD-1015","category":"Kitchen","brand":"SharpEdge","price":720000,"stock":21},
{"id":"16","tittle":"Hair Dryer","code":"PRD-1016","category":"Beauty","brand":"SilkGlow","price":310000,"stock":38},
{"id":"17","tittle":"Face Serum","code":"PRD-1017","category":"Beauty","brand":"PureSkin","price":185000,"stock":60},
{"id":"18","tittle":"Fitness Tracker","code":"PRD-1018","category":"Fitness","brand":"ActivePulse","price":679000,"stock":47},
{"id":"19","tittle":"Camping Tent","code":"PRD-1019","category":"Outdoor","brand":"TrailMax","price":1420000,"stock":13},
{"id":"20","tittle":"Portable Blender","code":"PRD-1020","category":"Kitchen","brand":"BlendIt","price":299000,"stock":50},
{"id":"21","tittle":"Sunglasses UV","code":"PRD-1021","category":"Fashion","brand":"ShadePro","price":195000,"stock":70},
{"id":"22","tittle":"Water Bottle","code":"PRD-1022","category":"Outdoor","brand":"HydroFlow","price":120000,"stock":92},
{"id":"23","tittle":"Laptop Sleeve","code":"PRD-1023","category":"Electronics","brand":"GuardTech","price":175000,"stock":58},
{"id":"24","tittle":"Desk Organizer","code":"PRD-1024","category":"Home","brand":"NeatSpace","price":95000,"stock":74},
{"id":"25","tittle":"Gaming Mouse","code":"PRD-1025","category":"Electronics","brand":"Apex","price":490000,"stock":26},
{"id":"26","tittle":"Smart Lamp","code":"PRD-1026","category":"Home","brand":"GlowBot","price":650000,"stock":36},
{"id":"27","tittle":"Pet Food Pack","code":"PRD-1027","category":"Pet","brand":"Petia","price":180000,"stock":44},
{"id":"28","tittle":"Notebook Set","code":"PRD-1028","category":"Stationery","brand":"WriteOn","price":67000,"stock":82},
{"id":"29","tittle":"Travel Adapter","code":"PRD-1029","category":"Electronics","brand":"GlobeTech","price":129000,"stock":39},
{"id":"30","tittle":"Wireless Charger","code":"PRD-1030","category":"Electronics","brand":"ChargeX","price":290000,"stock":58}
]